pygcode/__init__.py
pygcode/block.py
pygcode/comment.py
pygcode/exceptions.py
pygcode/gcodes.py
pygcode/line.py
pygcode/machine.py
pygcode/transform.py
pygcode/utils.py
pygcode/words.py
pygcode-0.2.0.data/scripts/pygcode-crop
pygcode-0.2.0.data/scripts/pygcode-norm
pygcode-0.2.0.dist-info/DESCRIPTION.rst
pygcode-0.2.0.dist-info/LICENSE.txt
pygcode-0.2.0.dist-info/METADATA
pygcode-0.2.0.dist-info/RECORD
pygcode-0.2.0.dist-info/WHEEL
pygcode-0.2.0.dist-info/metadata.json
pygcode-0.2.0.dist-info/top_level.txt
