Metadata-Version: 2.0
Name: pygcode
Version: 0.2.0
Summary: Basic g-code parser, interpreter, and encoder library.
Home-page: https://github.com/fragmuffin/pygcode
Author: Peter Boin
Author-email: peter.boin@gmail.com
License: GPLv3
Keywords: gcode,cnc,parser,interpreter
Platform: UNKNOWN
Classifier: Development Status :: 2 - Pre-Alpha
Classifier: Intended Audience :: Developers
Classifier: Intended Audience :: Manufacturing
Classifier: License :: OSI Approved :: GNU General Public License v3 (GPLv3)
Classifier: Natural Language :: English
Classifier: Operating System :: OS Independent
Classifier: Programming Language :: Python
Classifier: Programming Language :: Python :: 2
Classifier: Programming Language :: Python :: 3
Classifier: Topic :: Scientific/Engineering
Requires-Dist: argparse
Requires-Dist: euclid3
Requires-Dist: six
